pyhlld.py
setup.py
pyhlld.egg-info/PKG-INFO
pyhlld.egg-info/SOURCES.txt
pyhlld.egg-info/dependency_links.txt
pyhlld.egg-info/top_level.txt