Metadata-Version: 1.0
Name: pyhlld
Version: 0.1.1
Summary: Client library to interface with hlld servers
Home-page: https://github.com/armon/pyhlld
Author: Armon Dadgar
Author-email: armon.dadgar@gmail.com
License: MIT License
Keywords: hyperloglog,hll,hlld,client
Platform: UNKNOWN
Classifier: Development Status :: 4 - Beta
Classifier: Intended Audience :: Developers
Classifier: License :: OSI Approved :: MIT License
Classifier: Operating System :: POSIX
Classifier: Programming Language :: Python
Classifier: Topic :: Database
Classifier: Topic :: Internet
Classifier: Topic :: Software Development :: Libraries
